CRAM/__init__.py
CRAM/core.py
CRAM/parser.py
CRAM/test.py
CRAM/writer.py
sparse_cram-0.1.6.3.dist-info/METADATA
sparse_cram-0.1.6.3.dist-info/WHEEL
sparse_cram-0.1.6.3.dist-info/RECORD
