Metadata-Version: 2.1
Name: sparse-CRAM
Version: 0.1.6.3
Summary: A Basic Reader and Writer for CRAM format
Author: Ram Prakash Ayyam Perumal
Author-email: nuvi@umich.edu
Requires-Python: >=3.10
Classifier: Programming Language :: Python :: 3
Classifier: Programming Language :: Python :: 3.10
Classifier: Programming Language :: Python :: 3.11
Classifier: Programming Language :: Python :: 3.12
Classifier: Programming Language :: Python :: 3.13
Requires-Dist: scipy (>=1.15.0,<2.0.0)
